cococo/__init__.py
cococo-0.0.1.dist-info/LICENSE
cococo-0.0.1.dist-info/WHEEL
cococo-0.0.1.dist-info/METADATA
cococo-0.0.1.dist-info/RECORD
